Workbook

Sheet Nifty 500
A1: # | B1: Company Name | C1: NSE Symbol | D1: Sector (NSE Industry) | E1: ISIN | F1: My Pick
A2: 1 | B2: 360 ONE WAM Ltd. | C2: 360ONE | D2: Financial Services | E2: INE466L01038
A3: 2 | B3: 3M India Ltd. | C3: 3MINDIA | D3: Diversified | E3: INE470A01017
A4: 3 | B4: Aadhar Housing Finance Ltd. | C4: AADHARHFC | D4: Financial Services | E4: INE883F01010
A5: 4 | B5: Aarti Industries Ltd. | C5: AARTIIND | D5: Chemicals | E5: INE769A01020
A6: 5 | B6: Aavas Financiers Ltd. | C6: AAVAS | D6: Financial Services | E6: INE216P01012
A7: 6 | B7: ABB India Ltd. | C7: ABB | D7: Capital Goods | E7: INE117A01022
A8: 7 | B8: Abbott India Ltd. | C8: ABBOTINDIA | D8: Healthcare | E8: INE358A01014
A9: 8 | B9: ACC Ltd. | C9: ACC | D9: Construction Materials | E9: INE012A01025
A10: 9 | B10: ACME Solar Holdings Ltd. | C10: ACMESOLAR | D10: Power | E10: INE622W01025
A11: 10 | B11: Action Construction Equipment Ltd. | C11: ACE | D11: Capital Goods | E11: INE731H01025
A12: 11 | B12: Acutaas Chemicals Ltd. | C12: ACUTAAS | D12: Healthcare | E12: INE00FF01025
A13: 12 | B13: Adani Energy Solutions Ltd. | C13: ADANIENSOL | D13: Power | E13: INE931S01010
... A500: 499 | B500: Zydus Wellness Ltd. | C500: ZYDUSWELL | D500: Fast Moving Consumer Goods | E500: INE768C01028
B502: HOW TO USE: type x in the yellow "My Pick" column for every company you want analysed, then send the file back (or just message me the symbols).
B503: Example — a picked row would look like:
A504: e.g. | B504: Reliance Industries Ltd. | C504: RELIANCE | D504: Oil Gas & Consumable Fuels | E504: INE002A01018 | F504: x

Sheet Sector Summary
A1: Sector (NSE Industry) | B1: No. of Companies | C1: % of Index Count
A2: Automobile and Auto Components | B2: =COUNTIF('Nifty 500'!$D$2:$D$500,$A2) -> 38 | C2: =IFERROR(B2/$B$22,0) -> 0.076152305
A3: Capital Goods | B3: =COUNTIF('Nifty 500'!$D$2:$D$500,$A3) -> 62 | C3: =IFERROR(B3/$B$22,0) -> 0.1242485
A4: Chemicals | B4: =COUNTIF('Nifty 500'!$D$2:$D$500,$A4) -> 26 | C4: =IFERROR(B4/$B$22,0) -> 0.052104208
A5: Construction | B5: =COUNTIF('Nifty 500'!$D$2:$D$500,$A5) -> 13 | C5: =IFERROR(B5/$B$22,0) -> 0.026052104
A6: Construction Materials | B6: =COUNTIF('Nifty 500'!$D$2:$D$500,$A6) -> 11 | C6: =IFERROR(B6/$B$22,0) -> 0.022044088
A7: Consumer Durables | B7: =COUNTIF('Nifty 500'!$D$2:$D$500,$A7) -> 16 | C7: =IFERROR(B7/$B$22,0) -> 0.032064128
A8: Consumer Services | B8: =COUNTIF('Nifty 500'!$D$2:$D$500,$A8) -> 29 | C8: =IFERROR(B8/$B$22,0) -> 0.058116232
A9: Diversified | B9: =COUNTIF('Nifty 500'!$D$2:$D$500,$A9) -> 3 | C9: =IFERROR(B9/$B$22,0) -> 0.006012024
A10: Fast Moving Consumer Goods | B10: =COUNTIF('Nifty 500'!$D$2:$D$500,$A10) -> 28 | C10: =IFERROR(B10/$B$22,0) -> 0.056112224
A11: Financial Services | B11: =COUNTIF('Nifty 500'!$D$2:$D$500,$A11) -> 101 | C11: =IFERROR(B11/$B$22,0) -> 0.20240481
A12: Healthcare | B12: =COUNTIF('Nifty 500'!$D$2:$D$500,$A12) -> 48 | C12: =IFERROR(B12/$B$22,0) -> 0.096192385
A13: Information Technology | B13: =COUNTIF('Nifty 500'!$D$2:$D$500,$A13) -> 27 | C13: =IFERROR(B13/$B$22,0) -> 0.054108216
... A21: Textiles | B21: =COUNTIF('Nifty 500'!$D$2:$D$500,$A21) -> 5 | C21: =IFERROR(B21/$B$22,0) -> 0.01002004
A22: TOTAL | B22: =SUM(B2:B21) -> 499 | C22: =IFERROR(B22/$B$22,0) -> 1

Sheet Notes & Source
A1: Item | B1: Detail
A2: Source | B2: NSE Indices constituent file: ind_nifty500list.csv (nsearchives.nseindia.com/content/indices/ind_nifty500list.csv)
A3: Retrieved | B3: 22 August 2026
A4: Rows captured | B4: 499 of 500 constituents.
A5: Known gap | B5: The NSE file could only be read through a summarising web-fetch proxy, not downloaded directly. Repeated cross-checks by letter and by sector converged on these 499 names; roughly one constituent may still be absent. Verify against the NSE file before using this for anything binding.
A6: Sector labels | B6: These are NSE macro-economic "Industry" labels as published in the constituent file, not GICS sectors.
A7: Symbol note | B7: NSE trading symbols. On BSE the same companies trade under numeric scrip codes.
A8: Rebalancing | B8: Nifty 500 is reconstituted semi-annually (Jan/Feb and Jul/Aug cycles). This snapshot reflects the file as published on the retrieval date above.
A9: Not advice | B9: This workbook is reference data only. Nothing here is investment advice, and Claude is not a financial adviser.
